{
  "Dashboard": "Dashboard",
  "Sales": "Sales",
  "Projects":"Projects",
  "ProjectStatus":"Project Status",
  "ProjectTaskStatus":"Project Task Status",
  "ProjectType":"Project Type",
  "Type":"Type",
  "Contacts":"Contacts",
  "Configuration":"Configuration",
  "Conpany":"Company",
  "Industries":"Industries",
  "Clients":"Clients",
  "Leads":"Leads",
  "Opportunities":"Opportunities",
  "Application":"Aplication",
  "Save":"Save",
  "Cancel":"Cancel",
  "Name":"Name",
  "AddNew":"Add New",
  "Actions":"Actions",
  "NoDatas":"No datas"
}
